pipeline_connector/__init__.py
pipeline_connector/base.py
pipeline_connector/connectors.py
pipeline_connector/data_pipeline.py
pipeline_connector/manager.py
pipeline_connector-0.1.0.dist-info/LICENSE
pipeline_connector-0.1.0.dist-info/METADATA
pipeline_connector-0.1.0.dist-info/WHEEL
pipeline_connector-0.1.0.dist-info/top_level.txt
pipeline_connector-0.1.0.dist-info/RECORD
