Metadata-Version: 2.1
Name: pipeline-connector
Version: 0.1.0
Summary: A powerful Python package for connecting and orchestrating multiple data pipelines
Home-page: https://github.com/yourusername/pipeline-connector
Author: Krix Developer
Author-email: Krix Developer <developer@example.com>
License: MIT
Project-URL: Homepage, https://github.com/yourusername/pipeline-connector
Project-URL: Documentation, https://pipeline-connector.readthedocs.io
Project-URL: Repository, https://github.com/yourusername/pipeline-connector
Project-URL: Bug Tracker, https://github.com/yourusername/pipeline-connector/issues
Keywords: pipeline,data,processing,connector,orchestration
Classifier: Development Status :: 4 - Beta
Classifier: Intended Audience :: Developers
Classifier: License :: OSI Approved :: MIT License
Classifier: Programming Language :: Python :: 3
Classifier: Programming Language :: Python :: 3.8
Classifier: Programming Language :: Python :: 3.9
Classifier: Programming Language :: Python :: 3.10
Classifier: Programming Language :: Python :: 3.11
Classifier: Programming Language :: Python :: 3.12
Classifier: Topic :: Software Development :: Libraries :: Python Modules
Classifier: Topic :: System :: Distributed Computing
Requires-Python: >=3.8
License-File: LICENSE
Requires-Dist: typing-extensions >=4.0.0
Provides-Extra: dev
Requires-Dist: pytest >=7.0.0 ; extra == 'dev'
Requires-Dist: pytest-asyncio >=0.21.0 ; extra == 'dev'
Requires-Dist: black >=23.0.0 ; extra == 'dev'
Requires-Dist: isort >=5.12.0 ; extra == 'dev'
Requires-Dist: mypy >=1.0.0 ; extra == 'dev'
Requires-Dist: flake8 >=6.0.0 ; extra == 'dev'
